textual_vim/__init__.py
textual_vim/widget.py
textual_vim-0.1.0.dist-info/METADATA
textual_vim-0.1.0.dist-info/WHEEL
textual_vim-0.1.0.dist-info/licenses/LICENSE
textual_vim-0.1.0.dist-info/RECORD
