Metadata-Version: 2.3
Name: textual-vim
Version: 0.1.0
Summary: A Textual widget for a text area based on VIM
Project-URL: Homepage, https://github.com/davidbrochart/textual-vim
Project-URL: Source, https://github.com/davidbrochart/textual-vim
Project-URL: Issues, https://github.com/davidbrochart/textual-vim/issues
Project-URL: Pypi, https://pypi.org/project/textual-vim
Author-email: David Brochart <david.brochart@gmail.com>
License: MIT License
License-File: LICENSE
Keywords: textual
Classifier: Development Status :: 4 - Beta
Classifier: Intended Audience :: Developers
Classifier: License :: OSI Approved :: MIT License
Classifier: Programming Language :: Python
Classifier: Programming Language :: Python :: 3.8
Classifier: Programming Language :: Python :: 3.9
Classifier: Programming Language :: Python :: 3.10
Classifier: Programming Language :: Python :: 3.11
Classifier: Programming Language :: Python :: 3.12
Requires-Python: >=3.8
Requires-Dist: pyte>=0.8.2
Requires-Dist: rich
Requires-Dist: textual>=0.76.0
